hmath/__init__.py
hmath/test_hmath.py
hmath-5.0.6.dist-info/LICENSE
hmath-5.0.6.dist-info/METADATA
hmath-5.0.6.dist-info/WHEEL
hmath-5.0.6.dist-info/top_level.txt
hmath-5.0.6.dist-info/RECORD
