Metadata-Version: 2.1
Name: hmath
Version: 5.0.6
Summary: hmath that can use advanced mathematical functions.
Home-page: https://caleb7023.hmath.pro/home
Author: caleb7023
Project-URL: Bug Tracker, https://github.com/caleb7023/hmath
Keywords: hmath,math,python,caleb7023
Classifier: Programming Language :: Python :: 3
Classifier: License :: OSI Approved :: MIT License
Classifier: Operating System :: OS Independent
Requires-Python: >=3.0
License-File: LICENSE
